vue_project_ca_backend/__init__.py
vue_project_ca_backend/app.cp39-win_amd64.pyd
vue_project_ca_backend/init.sql
vue_project_ca_backend/static.cp39-win_amd64.pyd
vue_project_ca_backend/apis/__init__.py
vue_project_ca_backend/apis/projects/__init__.py
vue_project_ca_backend/apis/projects/serializers.cp39-win_amd64.pyd
vue_project_ca_backend/apis/projects/urls.cp39-win_amd64.pyd
vue_project_ca_backend/apis/projects/view.cp39-win_amd64.pyd
vue_project_ca_backend/apis/users/__init__.py
vue_project_ca_backend/apis/users/serializers.cp39-win_amd64.pyd
vue_project_ca_backend/apis/users/urls.cp39-win_amd64.pyd
vue_project_ca_backend/apis/users/utils.cp39-win_amd64.pyd
vue_project_ca_backend/apis/users/view.cp39-win_amd64.pyd
vue_project_ca_backend/base/__init__.py
vue_project_ca_backend/base/view.cp39-win_amd64.pyd
vue_project_ca_backend/base/auth/__init__.py
vue_project_ca_backend/base/auth/helper.cp39-win_amd64.pyd
vue_project_ca_backend/base/decorators/__init__.py
vue_project_ca_backend/base/decorators/helper.cp39-win_amd64.pyd
vue_project_ca_backend/base/log/__init__.py
vue_project_ca_backend/base/log/helper.cp39-win_amd64.pyd
vue_project_ca_backend/base/orm/__init__.py
vue_project_ca_backend/base/orm/helper.cp39-win_amd64.pyd
vue_project_ca_backend/base/plugins/__init__.py
vue_project_ca_backend/base/plugins/limiter_helper.cp39-win_amd64.pyd
vue_project_ca_backend/base/plugins/mail_helper.cp39-win_amd64.pyd
vue_project_ca_backend/base/plugins/plugins.cp39-win_amd64.pyd
vue_project_ca_backend/base/plugins/timer_helper.cp39-win_amd64.pyd
vue_project_ca_backend/base/plugins/license/__init__.py
vue_project_ca_backend/base/plugins/license/helper.cp39-win_amd64.pyd
vue_project_ca_backend/base/plugins/license/key.cp39-win_amd64.pyd
vue_project_ca_backend/base/plugins/license/view.cp39-win_amd64.pyd
vue_project_ca_backend/base/redis_helper/__init__.py
vue_project_ca_backend/base/redis_helper/helper.cp39-win_amd64.pyd
vue_project_ca_backend/base/utils/__init__.py
vue_project_ca_backend-2023.8.24.post16.dist-info/METADATA
vue_project_ca_backend-2023.8.24.post16.dist-info/WHEEL
vue_project_ca_backend-2023.8.24.post16.dist-info/top_level.txt
vue_project_ca_backend-2023.8.24.post16.dist-info/RECORD
