Metadata-Version: 2.1
Name: vue-project-ca-backend
Version: 2023.8.24.post16
Summary: ca授权
Home-page: https://gitee.com/bean_jun/vue-project-ca-backend
Author: Bean-jun
Author-email: 1342104001@qq.com
License: MIT License
Platform: UNKNOWN
Classifier: License :: OSI Approved :: MIT License
Classifier: Programming Language :: Python :: 3.8
Classifier: Programming Language :: Python :: 3.9
Classifier: Programming Language :: Python :: 3.10
Requires-Dist: Flask >=2.3.2
Requires-Dist: Flask-Caching >=2.0.2
Requires-Dist: Flask-Mail >=0.9.1
Requires-Dist: Flask-RESTful >=0.3.9
Requires-Dist: Flask-SQLAlchemy >=3.0.5
Requires-Dist: marshmallow >=3.19.0
Requires-Dist: Pillow >=9.5.0
Requires-Dist: PyJWT >=2.6.0
Requires-Dist: pycryptodome >=3.17
Requires-Dist: redis >=4.5.4
Requires-Dist: APScheduler >=3.10.1
Requires-Dist: Flask-Limiter >=3.3.1
